py2edw/mysql.py
py2edw/postgresql.py
py2edw-0.0.92.dist-info/LICENSE
py2edw-0.0.92.dist-info/METADATA
py2edw-0.0.92.dist-info/WHEEL
py2edw-0.0.92.dist-info/entry_points.txt
py2edw-0.0.92.dist-info/top_level.txt
py2edw-0.0.92.dist-info/RECORD
