Metadata-Version: 2.1
Name: py2edw
Version: 0.0.92
Summary: A high level Python wrapper for remotely connecting to SQL databases and querying using pandas dataframes.
Home-page: https://github.com/renzobecerra/py2edw
Author: Renzo Becerra
Author-email: rbecerra@nameless.ai
License: MIT
Platform: UNKNOWN
Classifier: License :: OSI Approved :: MIT License
Classifier: Programming Language :: Python :: 3
Classifier: Programming Language :: Python :: 3.7
Requires-Dist: psycopg2-binary
Requires-Dist: sshtunnel
Requires-Dist: pandas
Requires-Dist: mysql-connector-python
